apollo/__init__.py
apollo/client.py
example/__init__.py
example/get_config.py
python_apollo-0.0.3.dist-info/METADATA
python_apollo-0.0.3.dist-info/WHEEL
python_apollo-0.0.3.dist-info/top_level.txt
python_apollo-0.0.3.dist-info/RECORD
