Metadata-Version: 2.1
Name: python-apollo
Version: 0.0.3
Summary: Python3 Apollo Client
Home-page: https://github.com/rexyan/python-apollo
Author: RexYan
Author-email: rex_yan@126.com
License: MIT
Platform: all
Classifier: Development Status :: 4 - Beta
Classifier: Intended Audience :: Developers
Classifier: Topic :: Software Development :: Build Tools
Classifier: License :: OSI Approved :: MIT License
Classifier: Programming Language :: Python
Classifier: Programming Language :: Python :: 3.7
Classifier: Programming Language :: Python :: 3.8
Classifier: Programming Language :: Python :: 3.9
Requires-Dist: requests (>=2.23.0)
Requires-Dist: PyYAML (>=5.3.1)
